<page>
    <title>三浦海岸駅</title>
    <ns>0</ns>
    <id>27559</id>
    <revision>
      <id>95218465</id>
      <parentid>94630068</parentid>
      <timestamp>2023-05-15T14:33:35Z</timestamp>
      <contributor>
        <username>編集中</username>
        <id>650263</id>
      </contributor>
      <minor />
      <comment>png → svg</comment>
      <model>wikitext</model>
      <format>text/x-wiki</format>
      <text bytes="19813" xml:space="preserve">{{pp|small=y}}
{{駅情報
|社色 = #00bfff
|文字色 = white
|駅名 = 三浦海岸駅
|画像 = Miurakaigan Station 20210223 161027.jpg
|pxl = 300px
|画像説明 = 駅舎（2021年2月23日）
|地図 = {{Infobox mapframe|zoom=14|type=point|frame-width=300|marker=rail}}
|よみがな = みうらかいがん
|ローマ字 = Miurakaigan
|前の駅 = KK70 [[津久井浜駅|津久井浜]]
|駅間A = 1.5
|駅間B = 2.2
|次の駅 = [[三崎口駅|三崎口]] KK72
|駅番号 = {{駅番号r|KK|71|#00bfff|4||#00386d}}
|電報略号 =
|所属事業者 = [[京浜急行電鉄]]
|所属路線 = {{color|#00bfff|■}}[[京急久里浜線|久里浜線]]
|キロ程 = 11.2&amp;nbsp;km（[[堀ノ内駅|堀ノ内]]起点）&lt;br /&gt;[[品川駅|品川]]から63.5
|起点駅 =
|所在地 = [[神奈川県]][[三浦市]]南下浦町上宮田1497&lt;ref name="kotsu19920805"&gt;{{Cite news |title=私鉄沿線・いま 京浜急行三浦海岸駅 |newspaper=[[交通新聞]] |publisher=交通新聞社 |date=1992-08-05 |page=2 }}&lt;/ref&gt;
|緯度度 = 35 |緯度分 = 11 |緯度秒 = 17.1 |N(北緯)及びS(南緯) = N
|経度度 = 139 |経度分 = 39 |経度秒 = 12.1 |E(東経)及びW(西経) = E
|地図国コード = JP
|座標右上表示 = Yes
|駅構造 = 高架駅
|ホーム = 2面2線
|開業年月日 = [[1966年]]（[[昭和]]41年）[[7月7日]]&lt;ref name="kotsu19920805"/&gt;
|廃止年月日 =
|乗降人員 = &lt;ref group="!" name="kr02" /&gt;7,843
|統計年度 = 2020年
|備考 =
}}
[[ファイル:三浦海岸 2019年.jpg|thumb|「三浦海岸桜まつり」限定で桜色に変更された駅名看板（2019年2月）]]
'''三浦海岸駅'''（みうらかいがんえき）は、[[神奈川県]][[三浦市]]南下浦町上宮田にある[[京浜急行電鉄]][[京急久里浜線|久里浜線]]の[[鉄道駅|駅]]&lt;ref name="kotsu19920805"/&gt;。&lt;!--三浦市の駅は2か所のみであり、最北端と記述する必要性は感じない--&gt;[[駅ナンバリング|駅番号]]は'''KK71'''。

当駅から小松ヶ池公園までの線路沿いで、毎年春に「三浦海岸桜まつり」が開催される。これを記念して2014年から、桜まつりの開催期間中は駅正面の駅名看板を桜色に変更している&lt;ref&gt;{{PDFlink|[http://www.keikyu.co.jp/file.jsp?assets/pdf/company/news/2013/company-miura_20140205.pdf 今年も「三浦海岸の河津桜」でひと足早い春を満喫！初の「ライトアップ」や「春色の駅名看板」でおもてなしします]}} - 京浜急行電鉄&lt;/ref&gt;。

== 歴史 ==
計画時の駅名は地名に基づく「上宮田駅」であったが、下浦海岸に因むこの名称&lt;ref name="keikyu"&gt;{{PDFlink|[http://www.keikyu.co.jp/file.jsp?assets/pdf/information/magazine/kakueki/local_vol11.pdf 京急線普通電車の旅 Vol.11]}}12ページ - 京浜急行電鉄&lt;/ref&gt;とし、延長区間を三浦海岸線と呼びPRに努めた。
* [[1966年]]（[[昭和]]41年）[[7月7日]] - 久里浜線の終着駅として開業&lt;ref name="kotsu19920805"/&gt;&lt;ref name="kr2021-111"&gt;{{Cite web|url=https://www.keikyu.co.jp/company/pdf/handbook2021-2022_P107-122.pdf|archiveurl=|title=京急グループ会社要覧 2021 - 2022|archivedate=|page=111|accessdate=2022-09-03|publisher=京浜急行電鉄|format=PDF|language=日本語}}&lt;/ref&gt;。
* [[1969年]]（昭和44年）6月 - ホーム有効長を12両編成分に延伸。
* [[1975年]]（昭和50年）[[4月26日]] - 久里浜線が三崎口駅まで延伸、中間駅となる&lt;ref&gt;{{Cite news |和書|title=関東の私鉄に二つの新線 |newspaper=[[交通新聞]] |publisher=交通協力会 |date=1975-04-23 |page=2 }}&lt;/ref&gt;&lt;ref name="kr2021-111" /&gt;。
* [[2016年]]（[[平成]]28年）[[10月24日]] - 下りホーム8号車で[[三菱重工業]]製[[ホームドア]]「どこでもドア」の実証試験を開始&lt;ref&gt;{{Cite press release|和書|url=http://www.keikyu.co.jp/file.jsp?assets/pdf/company/news/2016/20161014HP_16136NN.pdf|archiveurl=https://web.archive.org/web/20180906195632/http://www.keikyu.co.jp/file.jsp?assets/pdf/company/news/2016/20161014HP_16136NN.pdf|format=PDF|language=日本語|title=「マルチドア対応ホームドア（どこでもドア®︎）」 実証実験京急久里浜線三浦海岸駅にて10月24日（月）始発より開始します|publisher=京浜急行電鉄／三菱重工業|date=2016-10-14|accessdate=2020-07-16|archivedate=2018-09-06}}&lt;/ref&gt;&lt;ref name="kr2021-117"&gt;{{Cite web|url=https://www.keikyu.co.jp/company/pdf/handbook2021-2022_P107-122.pdf|archiveurl=|title=京急グループ会社要覧 2021 - 2022|archivedate=|page=117|accessdate=2022-09-03|publisher=京浜急行電鉄|format=PDF|language=日本語}}&lt;/ref&gt;。翌年9月まで実施された。
* [[2017年]]（平成29年）[[2月10日]] - [[接近メロディ]]を導入。「[[岬めぐり]]」が採用された&lt;ref name="kr2017-001"&gt;{{Cite web|url=http://www.keikyu.co.jp/company/news/2016/20160127HP_16206YM.html|archiveurl=https://web.archive.org/web/20170918202159/http://www.keikyu.co.jp/company/news/2016/20160127HP_16206YM.html|title=今年も三浦海岸に河津桜の季節がやってくる!「三浦海岸 河津桜とまぐろ満喫の旅」キャンペーン開催夜間ライトアップや貸切列車の運行などイベント盛りだくさん!!|archivedate=2017-09-18|page=|accessdate=2022-09-03|publisher=京浜急行電鉄株式会社|format=PDF|language=日本語|deadlink=2022-09-03}}&lt;/ref&gt;。
* [[2018年]]（平成30年）[[5月26日]] - 新駅舎の使用を開始。
* [[2019年]]（[[令和]]元年）[[7月8日]] - 京急グループ120周年記念事業の一環としてアニメ放送20周年を迎える[[ONE PIECE (アニメ)|ワンピース]]と京浜急行電鉄とのコラボが実施され、同年9月16日までの期間限定で当駅名看板に副駅名称として「'''三浦〝海賊王に俺はなるっ!!!!〟駅'''」が導入される&lt;ref&gt;{{Cite web |date=2019-07-01 |url=https://www.keikyu.co.jp/company/news/2019/20190701HP_19079AK.html |title=ニュースリリース アニメ『ワンピース』20周年×YOKOSUKA×KEIKYU120周年 京急“宴”線・横須賀市内全体でコラボ実施！ 謎解きミッションラリーを開催！ オリジナルグッズ・グルメも！ |website=KEIKYU WEB |accessdate=2019-09-13 }}&lt;/ref&gt;。

== 駅構造 ==
[[相対式ホーム]]2面2線を有する[[高架駅]]である。ホームは北東から南西へと延びている。[[改札]]は1箇所で、ホームへは[[階段]]と[[エレベーター]]で連絡している。当駅の起点方（北側）は[[複線]]、終点方は[[単線]]区間（ただし複線化用地は確保されている）となっており、一部時間帯の下り列車は[[列車交換]]のため4 - 5分ほど停車する場合がある。

発着する列車はすべて8両編成だが、12両編成の停車が可能なホーム（[[有効長]]約220メートル）を持つ。これはかつて、海水浴客輸送最盛期に列車を同一ホームに2本停車させ旅客整理を行っていた名残である。

下り[[終電|最終電車]]の後に2本到着する当駅止まりの下り列車は翌早朝まで留置され、始発の上り列車として発車する。

=== のりば ===
&lt;!--公式サイトの駅構内図に基づく--&gt;
{|class="wikitable"
!番線!!路線!!方向!!行先
|-
!1
|rowspan="2"|[[File:Number prefix Keikyū.svg|15px|KK]] 久里浜線
|style="text-align:center"|下り
|[[三崎口駅|三崎口]]行き
|-
!2
|style="text-align:center"|上り
|[[横浜駅|横浜]]・[[品川駅|品川]]方面
|}
&lt;gallery&gt;
Miurakaigan Station entrance 20120315.jpg|旧駅舎（2012年3月15日）
Miurakaigan Station platform.jpg|ホーム（2019年9月）
Keikyu-railway-kurihama-line-Miura-kaigan-station-platform.jpg|ホーム有効長 12両編成分（今は柵が設置され入れない）
Miurakaigan Station gate 20210223 161114.jpg|改札口（2021年2月23日）
Keikyu Miurakaigan sta 002.jpg|旧改札口
三浦海岸ホームドア閉扉時.jpg|実証試験が行われたホームドア「どこでもドア」
&lt;/gallery&gt;

=== 接近メロディ ===
「三浦海岸 河津桜とまぐろ満喫の旅」キャンペーンの開催に合わせ、[[2017年]][[2月10日]]から、三浦市[[三崎町 (神奈川県)|三崎]]地区が舞台となった[[山本コウタロー]]とウィークエンドの楽曲「[[岬めぐり]]」をアレンジしたものを[[発車メロディ#接近メロディ|接近メロディ]]として使用している&lt;ref&gt;[http://www.keikyu.co.jp/company/news/2016/20160127HP_16206YM.html 「今年も三浦海岸に河津桜の季節がやってくる！「三浦海岸 河津桜とまぐろ満喫の旅」キャンペーン開催夜間ライトアップや貸切列車の運行などイベント盛りだくさん！！] 京急電鉄&lt;/ref&gt;&lt;ref group="注釈"&gt;同曲は三崎口駅でも[[2008年]][[12月10日]]から2017年[[1月12日]]まで同じく接近メロディとして使用されていたが、同駅のものとは別のアレンジを使用している。&lt;/ref&gt;。メロディは[[スイッチ (音楽制作会社)|スイッチ]]の制作で、編曲は[[塩塚博]]が手掛けた&lt;ref&gt;{{Cite web|title=三浦海岸駅接近メロディ「岬めぐり」制作|url=http://www.switching.co.jp/news/273|website=株式会社スイッチオフィシャルサイト|accessdate=2019-10-16|language=ja|last=|publisher=株式会社スイッチ}}&lt;/ref&gt;。

== 利用状況 ==
[[2020年]]（令和2年）度の1日平均[[乗降人員|'''乗降'''人員]]は'''7,843人'''であり&lt;ref group="!" name="kr02"&gt;{{Cite web|url=https://www.keikyu.co.jp/company/pdf/handbook2021-2022_P019-042.pdf|archiveurl=|title=京急グループ会社要覧 2021 - 2022|archivedate=|page=31|accessdate=2021-09-28|publisher=京浜急行電鉄|format=PDF|language=日本語}}&lt;/ref&gt;&lt;ref group="#" name="r03" /&gt;、京急線全72駅中57位。

近年の1日平均'''乗降'''人員と[[乗降人員#乗車人員|'''乗車'''人員]]は下記の通り。
{|class="wikitable" style="text-align:right"
|+年度別1日平均乗降・乗車人員
!年度
!1日平均&lt;br /&gt;乗降人員&lt;ref&gt;[https://www.train-media.net/report.html レポート] - 関東交通広告協議会&lt;/ref&gt;
!1日平均&lt;br /&gt;乗車人員&lt;ref&gt;[https://www.pref.kanagawa.jp/documents/46041/15.pdf 神奈川県県勢要覧] - 神奈川県&lt;/ref&gt;
!備考
|-
|1990年（平成{{0}}2年）
|&lt;ref group="#" name="r03" /&gt;15,365
|
|
|-
|1995年（平成{{0}}7年）
|&lt;ref group="#" name="r03" /&gt;14,719
|7,358
|&lt;ref group="*"&gt;{{PDFlink|[http://www.pref.kanagawa.jp/uploaded/attachment/784899.pdf 線区別駅別乗車人員（1日平均）の推移]}} - 24ページ&lt;/ref&gt;
|-
|1998年（平成10年）
|&lt;ref group="#" name="r03" /&gt;13,639
|6,766
|&lt;ref group="*"&gt;神奈川県県勢要覧（平成12年度）&lt;/ref&gt;
|-
|1999年（平成11年）
|&lt;ref group="#" name="r03" /&gt;13,383
|6,693
|&lt;ref group="*" name="toukei2001"&gt;{{PDFlink|[http://www.pref.kanagawa.jp/uploaded/attachment/369557.pdf 神奈川県県勢要覧（平成13年度）]}} - 227ページ&lt;/ref&gt;
|-
|2000年（平成12年）
|&lt;ref group="#" name="r03" /&gt;13,205
|6,600
|&lt;ref group="*" name="toukei2001" /&gt;
|-
|2001年（平成13年）
|&lt;ref group="#" name="r03" /&gt;13,242
|6,605
|&lt;ref group="*"&gt;{{PDFlink|[http://www.pref.kanagawa.jp/uploaded/attachment/369552.pdf 神奈川県県勢要覧（平成14年度）]}} - 225ページ&lt;/ref&gt;
|-
|2002年（平成14年）
|&lt;ref group="#" name="r03" /&gt;12,942
|6,463
|&lt;ref group="*"&gt;{{PDFlink|[http://www.pref.kanagawa.jp/uploaded/attachment/369547.pdf 神奈川県県勢要覧（平成15年度）]}} - 225ページ&lt;/ref&gt;
|-
|2003年（平成15年）
|&lt;ref group="#" name="r03" /&gt;12,879
|6,410
|&lt;ref group="*"&gt;{{PDFlink|[http://www.pref.kanagawa.jp/uploaded/attachment/369542.pdf 神奈川県県勢要覧（平成16年度）]}} - 225ページ&lt;/ref&gt;
|-
|2004年（平成16年）
|&lt;ref group="#" name="r03" /&gt;12,665
|6,314
|&lt;ref group="*"&gt;{{PDFlink|[http://www.pref.kanagawa.jp/uploaded/attachment/369533.pdf 神奈川県県勢要覧（平成17年度）]}} - 227ページ&lt;/ref&gt;
|-
|2005年（平成17年）
|&lt;ref group="#" name="r03" /&gt;12,636
|6,299
|&lt;ref group="*"&gt;{{PDFlink|[http://www.pref.kanagawa.jp/uploaded/attachment/369528.pdf 神奈川県県勢要覧（平成18年度）]}} - 227ページ&lt;/ref&gt;
|-
|2006年（平成18年）
|&lt;ref group="#" name="r03" /&gt;12,726
|6,352
|&lt;ref group="*"&gt;{{PDFlink|[http://www.pref.kanagawa.jp/uploaded/attachment/369523.pdf 神奈川県県勢要覧（平成19年度）]}} - 229ページ&lt;/ref&gt;
|-
|2007年（平成19年）
|&lt;ref group="#" name="r03" /&gt;12,842
|6,407
|&lt;ref group="*"&gt;{{PDFlink|[http://www.pref.kanagawa.jp/uploaded/attachment/35540.pdf 神奈川県県勢要覧（平成20年度）]}} - 233ページ&lt;/ref&gt;
|-
|2008年（平成20年）
|&lt;ref group="#" name="r03" /&gt;13,021
|6,445
|&lt;ref group="*"&gt;{{PDFlink|[http://www.pref.kanagawa.jp/uploaded/attachment/773803.pdf 神奈川県県勢要覧（平成21年度）]}} - 243ページ&lt;/ref&gt;
|-
|2009年（平成21年）
|&lt;ref group="#" name="r03" /&gt;12,686
|6,277
|&lt;ref group="*"&gt;{{PDFlink|[http://www.pref.kanagawa.jp/uploaded/attachment/161682.pdf 神奈川県県勢要覧（平成22年度）]|1.38MB}} - 241ページ&lt;/ref&gt;
|-
|2010年（平成22年）
|&lt;ref group="#" name="r03" /&gt;12,233
|6,057
|&lt;ref group="*"&gt;{{PDFlink|[http://www.pref.kanagawa.jp/uploaded/attachment/427362.pdf 神奈川県県勢要覧（平成23年度）]|2.36MB}} - 241ページ&lt;/ref&gt;
|-
|2011年（平成23年）
|&lt;ref group="#" name="r03" /&gt;11,735
|5,799
|&lt;ref group="*"&gt;{{PDFlink|[http://www.pref.kanagawa.jp/uploaded/attachment/706868.pdf 神奈川県県勢要覧（平成24年度）]|830KB}} - 237ページ&lt;/ref&gt;
|-
|2012年（平成24年）
|&lt;ref group="#" name="r03" /&gt;11,842
|5,858
|&lt;ref group="*"&gt;{{PDFlink|[http://www.pref.kanagawa.jp/uploaded/attachment/707631.pdf 神奈川県県勢要覧（平成25年度）]|509KB}} - 239ページ&lt;/ref&gt;
|-
|2013年（平成25年）
|&lt;ref group="#" name="r03" /&gt;11,813
|5,840
|&lt;ref group="*"&gt;{{PDFlink|[http://www.pref.kanagawa.jp/uploaded/attachment/762227.pdf 神奈川県県勢要覧（平成26年度）]}} - 241ページ&lt;/ref&gt;
|-
|2014年（平成26年）
|&lt;ref group="#" name="r03" /&gt;11,527
|5,685
|&lt;ref group="*"&gt;{{PDFlink|[http://www.klnet.pref.kanagawa.jp/resource/org_0101/pol_20160609_001_15.pdf 神奈川県県勢要覧（平成27年度）]|536KB}} - 241ページ&lt;/ref&gt;
|-
|2015年（平成27年）
|&lt;ref group="#" name="r03" /&gt;11,701
|5,766
|&lt;ref group="*"&gt;{{PDFlink|[http://www.pref.kanagawa.jp/uploaded/attachment/877254.pdf 神奈川県県勢要覧（平成28年度）]|533KB}} - 249ページ&lt;/ref&gt;
|-
|2016年（平成28年）
|&lt;ref group="#" name="r03" /&gt;11,658
|5,753
|&lt;ref group="*"&gt;{{PDFlink|[http://www.pref.kanagawa.jp/docs/x6z/tc10/documents/15.pdf 神奈川県県勢要覧（平成29年度）]}} - 241ページ&lt;/ref&gt;
|-
|2017年（平成29年）
|&lt;ref group="#" name="r03" /&gt;11,681
|5,766
|&lt;ref group="*"&gt;{{PDFlink|[https://www.pref.kanagawa.jp/documents/3406/15-30.pdf 神奈川県県勢要覧（平成30年度）]}} - 225ページ&lt;/ref&gt;
|-
|2018年（平成30年）
|&lt;ref group="#" name="r03" /&gt;11,458
|5,652
|&lt;ref group="*"&gt;{{PDFlink|[https://www.pref.kanagawa.jp/documents/46041/15.pdf 神奈川県県勢要覧（令和元年度）]}} - 225ページ&lt;/ref&gt;
|-
|2019年（令和元年）
|&lt;ref group="#" name="r03" /&gt;10,981
|5,410
|&lt;ref group="*"&gt;{{PDFlink|[https://www.pref.kanagawa.jp/documents/46041/202015.pdf 神奈川県県勢要覧（令和2年度）]}} - 225ページ&lt;/ref&gt;
|-
|2020年（令和{{0}}2年）
|&lt;ref group="#" name="r03"&gt;{{Cite web|url=http://www.city.miura.kanagawa.jp/digital/toukei/documents/r02-11koutsu_unyu.xlsx|title=令和2年度版三浦市統計書【11】交通・運輸|page=|format=xls|publisher=三浦市|accessdate=2022-09-03|archiveurl=https://warp.ndl.go.jp/info:ndljp/pid/12264224/www.city.miura.kanagawa.jp/digital/toukei/documents/r02-11koutsu_unyu.xlsx|archivedate=2022-05-09}}&lt;/ref&gt;7,843
|
|
|}

== 駅周辺 ==
{{See also|三浦海岸}}
当駅は三浦市北東部に位置する。周辺には住宅団地などがあるほか、小規模な商業施設や公共施設が集まる。駅名の由来となっている[[三浦海岸]]までは400mほどである。駅正面は[[バスターミナル]]となっている。
&lt;!--チェーン店を含む飲食店、コンビニ、個人商店などは記載しない--&gt;
* 三浦海岸[[海水浴場]]
* [[京急ストア]]三浦海岸店 -（後に三浦海岸駅前店（旧・[[ユニオネックス#店舗・業態|ヨコサン]]）を統合）
* 三浦市役所南下浦出張所
* 南下浦市民センター（2022年10月閉館&lt;ref&gt;{{Cite web |date= 2022-11-02|url=https://www.kanaloco.jp/news/government/article-947174.html|title= 樹齢100年の大木 大半伐採へ 三浦・市民センター跡地|publisher= 神奈川新聞|accessdate=2022-11-02}}&lt;/ref&gt;）
* [[三崎警察署]]三浦海岸駅前交番
* 南下浦郵便局
* [[三浦マホロバ温泉]]（マホロバマインズ三浦）
* [[国道134号]]
* [[神奈川県道214号武上宮田線]]
* [[神奈川県道215号上宮田金田三崎港線]]

== バス路線 ==
駅前バスロータリー内の「'''三浦海岸駅'''」が最寄り[[バス停留所|バス停]]。[[京浜急行バス]]により周辺地区への路線が運行されている&lt;ref name="bus01"&gt;[https://www.keikyu-bus.co.jp/line/root_stop/miurakaigan.html 三浦海岸駅 | のりば案内]、京浜急行バス株式会社、2022年9月3日閲覧&lt;/ref&gt;。三崎口駅が開業するまでは[[三浦半島]]南部へのアクセスを担うバス路線の拠点駅であった。発着する路線の詳細は[[京浜急行バス三崎営業所]]を参照。

* 1番乗り場（全路線引橋・[[油壺]]入口経由）
** [[京浜急行バス三崎営業所#三浦海岸線|海30]] - [[京浜急行バス三崎営業所|三崎東岡]]行
** [[京浜急行バス三崎営業所#三浦海岸線|海31]] - [[三崎漁港|三崎港]]行
* 2番乗り場
** [[京浜急行バス三崎営業所#剱崎線|海34]] - [[剱崎]]行
** [[京浜急行バス三崎営業所#剱崎線|海35]] - 三崎東岡行（剱崎・三崎港経由）
* 3番乗り場
** [[京浜急行バス三崎営業所#三浦海岸線|衣2]] - 衣笠十字路行
** [[京浜急行バス三崎営業所#横須賀市民病院線|海3]] - [[横須賀市立市民病院|横須賀市民病院]]行

== 隣の駅 ==
; 京浜急行電鉄
: [[File:Number prefix Keikyū.svg|15px|KK]] 久里浜線
:: {{Color|#049c5e|□}}「[[ウィング号 (京急)|モーニング・ウィング号]]」（上りのみ）
::: [[横須賀中央駅]] (KK59) ← '''三浦海岸駅 (KK71)'''
:: {{Color|#049c5e|□}}「[[ウィング号 (京急)|イブニング・ウィング号]]」（下りのみ）・{{Color|#049c5e|■}}快特・{{Color|#e8334a|■}}特急
::: [[津久井浜駅]] (KK70) - '''三浦海岸駅 (KK71)''' - [[三崎口駅]] (KK72)

== 脚注 ==
{{脚注ヘルプ}}
=== 注釈 ===
{{Reflist|group="注釈"}}
=== 出典 ===
{{Reflist}}
;神奈川県県勢要覧
{{Reflist|group="*"|3}}
;三浦市統計書
{{Reflist|group="#"|2}}
;京急電鉄の1日平均乗降人員
{{Reflist|group="!"|2}}

== 関連項目 ==
{{commonscat|Miurakaigan Station}}
* [[日本の鉄道駅一覧]]

== 外部リンク ==
* {{外部リンク/京浜急行電鉄駅|駅番号=KK71}}

{{京急久里浜線}}
{{DEFAULTSORT:みうらかいかん}}

[[Category:神奈川県の鉄道駅]]
[[Category:日本の鉄道駅 み|うらかいかん]]
[[Category:京浜急行電鉄の鉄道駅]]
[[Category:1966年開業の鉄道駅]]
[[Category:三浦市の建築物|みうらかいかんえき]]</text>
      <sha1>kqqfe9wlzw5tky5qxe2r26sulxsm0ls</sha1>
    </revision>
  </page>
  